definance/__init__.py
definance/classes.py
definance/exceptions.py
definance/exchange.py
definance/symbols.py
definance/url.py
definance/utils.py
definance-0.1.dist-info/LICENSE
definance-0.1.dist-info/METADATA
definance-0.1.dist-info/WHEEL
definance-0.1.dist-info/top_level.txt
definance-0.1.dist-info/RECORD
