Metadata-Version: 2.1
Name: definance
Version: 0.1
License-File: LICENSE
Requires-Dist: requests
